aiohttp_cas/__init__.py
aiohttp_cas/handlers.py
aiohttp_cas/log.py
aiohttp_cas/utils.py
aiohttp_cas/validators.py
aiohttp_cas-0.2.3.dist-info/DESCRIPTION.rst
aiohttp_cas-0.2.3.dist-info/METADATA
aiohttp_cas-0.2.3.dist-info/RECORD
aiohttp_cas-0.2.3.dist-info/WHEEL
aiohttp_cas-0.2.3.dist-info/metadata.json
aiohttp_cas-0.2.3.dist-info/top_level.txt
