Metadata-Version: 2.0
Name: aiohttp-cas
Version: 0.2.3
Summary: CAS 1/2/3 authentication middleware for aiohttp.web
Home-page: https://github.com/bard-it/aiohttp_cas/
Author: G. Ryan Sablosky
Author-email: gsablosky@bard.edu
License: MIT
Download-URL: https://github.com/bard-it/aiohttp_cas/archive/0.2.3.tar.gz
Platform: UNKNOWN
Classifier: License :: OSI Approved :: MIT License
Classifier: Intended Audience :: Developers
Classifier: Programming Language :: Python
Classifier: Programming Language :: Python :: 3
Classifier: Programming Language :: Python :: 3.5
Classifier: Programming Language :: Python :: 3.6
Classifier: Topic :: Internet :: WWW/HTTP
Requires-Dist: aiohttp (<3.2,>=2)
Requires-Dist: aiohttp-session
Requires-Dist: lxml
